py_inception/__init__.py
py_inception/abstract.py
py_inception/architect.py
py_inception/exporter.py
py_inception/extractor.py
py_inception/htmltemplate.py
py_inception/maze.py
py_inception-0.0.3.dist-info/LICENSE
py_inception-0.0.3.dist-info/WHEEL
py_inception-0.0.3.dist-info/METADATA
py_inception-0.0.3.dist-info/RECORD
