Metadata-Version: 2.1
Name: py_inception
Version: 0.0.3
Summary: Python introspection tool 
Author-email: Sergey Shirobokih <divetoh@yandex.ru>
Requires-Python: >=3.10
Classifier: License :: OSI Approved :: MIT License
Project-URL: Home, https://github.com/divetoh/py-inception
